sample_bot/__init__.py
sample_bot/run.py
slack_invoker/__init__.py
slack_invoker/invoke.py
slack_invoker/parse.py
slack_invoker/test_parse.py
slack_invoker-0.1.4.dist-info/LICENSE
slack_invoker-0.1.4.dist-info/METADATA
slack_invoker-0.1.4.dist-info/WHEEL
slack_invoker-0.1.4.dist-info/top_level.txt
slack_invoker-0.1.4.dist-info/RECORD
